canaveral_cli/__init__.py
canaveral_cli/__main__.py
canaveral_cli/cli.py
canaveral_cli/create_oam.py
canaveral_cli/cue_parser.py
canaveral_cli/data/oam_types/component/cron-task.json
canaveral_cli/data/oam_types/component/daemon.json
canaveral_cli/data/oam_types/component/k8s-objects.json
canaveral_cli/data/oam_types/component/task.json
canaveral_cli/data/oam_types/component/webservice.json
canaveral_cli/data/oam_types/policy/apply-once.json
canaveral_cli/data/oam_types/policy/garbage-collect.json
canaveral_cli/data/oam_types/policy/override.json
canaveral_cli/data/oam_types/policy/read-only.json
canaveral_cli/data/oam_types/policy/replication.json
canaveral_cli/data/oam_types/policy/resource-update.json
canaveral_cli/data/oam_types/policy/shared-resource.json
canaveral_cli/data/oam_types/policy/take-over.json
canaveral_cli/data/oam_types/policy/topology.json
canaveral_cli/data/oam_types/trait/annotations.json
canaveral_cli/data/oam_types/trait/command.json
canaveral_cli/data/oam_types/trait/container-image.json
canaveral_cli/data/oam_types/trait/cpuscaler.json
canaveral_cli/data/oam_types/trait/env.json
canaveral_cli/data/oam_types/trait/expose.json
canaveral_cli/data/oam_types/trait/gateway.json
canaveral_cli/data/oam_types/trait/hostalias.json
canaveral_cli/data/oam_types/trait/hpa.json
canaveral_cli/data/oam_types/trait/init-container.json
canaveral_cli/data/oam_types/trait/k8s-update-strategy.json
canaveral_cli/data/oam_types/trait/labels.json
canaveral_cli/data/oam_types/trait/lifecycle.json
canaveral_cli/data/oam_types/trait/pure-ingress.json
canaveral_cli/data/oam_types/trait/resource.json
canaveral_cli/data/oam_types/trait/scaler.json
canaveral_cli/data/oam_types/trait/service-account.json
canaveral_cli/data/oam_types/trait/sidecar.json
canaveral_cli/data/oam_types/trait/startup-probe.json
canaveral_cli/data/oam_types/trait/storage.json
canaveral_cli/data/oam_types/trait/topologyspreadconstraints.json
canaveral_cli-0.1.7.dist-info/entry_points.txt
canaveral_cli-0.1.7.dist-info/LICENSE
canaveral_cli-0.1.7.dist-info/WHEEL
canaveral_cli-0.1.7.dist-info/METADATA
canaveral_cli-0.1.7.dist-info/RECORD
